brainpylib/cpu_ops.cp39-win_amd64.pyd
brainpylib/__init__.py
brainpylib-0.3.1.dist-info/DELVEWHEEL
brainpylib-0.3.1.dist-info/LICENSE
brainpylib-0.3.1.dist-info/METADATA
brainpylib-0.3.1.dist-info/RECORD
brainpylib-0.3.1.dist-info/top_level.txt
brainpylib-0.3.1.dist-info/WHEEL
brainpylib.libs/.load-order-brainpylib-0.3.1
brainpylib.libs/D3DCompiler_47-6e70f42ffeb2f4224a040c64ffdd044c.dll
brainpylib.libs/msvcp140-5c8f8e1c94a5eb96830ed0042bd53f31.dll
brainpylib.libs/msvcp140d-28781d9d867e18999b60361fb04ddf58.dll
brainpylib.libs/taichi_c_api-54d02e81f8ec99c72397964ab4a84a2f.dll
brainpylib.libs/ucrtbased-c7f613574383dc6e5bf7393d37b9a81a.dll
brainpylib.libs/vcruntime140d-ee813093b8081d7ae00f24e453343145.dll
brainpylib.libs/vcruntime140_1d-43011d6381e5a91a2cd04830a31a10e7.dll
