Metadata-Version: 2.1
Name: brainpylib
Version: 0.3.1
Summary: C++/CUDA Library for BrainPy
Home-page: https://github.com/brainpy/BrainPy
Author: BrainPy team
Author-email: chao.brain@qq.com
License: GPL-3.0 license
Keywords: event-driven computation,sparse computation,brainpy
Classifier: Natural Language :: English
Classifier: Operating System :: OS Independent
Classifier: Programming Language :: Python
Classifier: Programming Language :: Python :: 3
Classifier: Programming Language :: Python :: 3.8
Classifier: Programming Language :: Python :: 3.9
Classifier: Programming Language :: Python :: 3.10
Classifier: Programming Language :: Python :: 3.11
Classifier: Intended Audience :: Science/Research
Classifier: License :: OSI Approved :: Apache Software License
Classifier: Topic :: Scientific/Engineering :: Bio-Informatics
Classifier: Topic :: Scientific/Engineering :: Mathematics
Classifier: Topic :: Scientific/Engineering :: Artificial Intelligence
Classifier: Topic :: Software Development :: Libraries
Requires-Python: >=3.8,<3.12
License-File: LICENSE
Provides-Extra: test
Requires-Dist: pytest ; extra == 'test'
